CMSMonitoring/NATS.py
CMSMonitoring/StompAMQ.py
CMSMonitoring/StompAMQ7.py
CMSMonitoring/Validator.py
CMSMonitoring/__init__.py
CMSMonitoring/amq_sender.py
CMSMonitoring/cmsmonit_size.py
CMSMonitoring/datasources_list.py
CMSMonitoring/grafana_duplicator.py
CMSMonitoring/grafana_textpanel_propagation.py
CMSMonitoring/grafanamanager.py
CMSMonitoring/hs06corehr.py
CMSMonitoring/monit.py
CMSMonitoring/openstack_accounting.py
CMSMonitoring/openstack_accounting_cmsvoc.py
CMSMonitoring/rucio_quotas.py
cmsmonitoring-0.6.13.data/scripts/monit
cmsmonitoring-0.6.13.dist-info/licenses/LICENSE
cmsmonitoring-0.6.13.dist-info/METADATA
cmsmonitoring-0.6.13.dist-info/WHEEL
cmsmonitoring-0.6.13.dist-info/top_level.txt
cmsmonitoring-0.6.13.dist-info/RECORD
