Metadata-Version: 2.4
Name: CMSMonitoring
Version: 0.6.13
Summary: CMS Monitoring utilities
Home-page: https://github.com/dmwm/CMSMonitoring
Author: Valentin Kuznetsov
Author-email: vkuznet@gmail.com
License: MIT
Classifier: Programming Language :: Python
Classifier: Operating System :: OS Independent
Classifier: License :: OSI Approved :: MIT License
License-File: LICENSE
Requires-Dist: setuptools
Requires-Dist: click
Requires-Dist: stomp.py<8.0.0,>=6.1.1
Requires-Dist: jsonschema>=4.20.0
Requires-Dist: nats-py; python_version >= "3.7"
Dynamic: author
Dynamic: author-email
Dynamic: classifier
Dynamic: description
Dynamic: home-page
Dynamic: license
Dynamic: license-file
Dynamic: requires-dist
Dynamic: summary
